scripts/__main__.py
neorick/__init__.py
neorick-1.2.2.dist-info/entry_points.txt
neorick-1.2.2.dist-info/METADATA
neorick-1.2.2.dist-info/WHEEL
neorick-1.2.2.dist-info/RECORD
