Metadata-Version: 2.3
Name: neorick
Version: 1.2.2
Summary: A system monitoring and reporting tool
Author: José Henrique Ferreira De Souza
Author-email: henriqueferreiraaf56@gmail.com
Requires-Python: >=3.13
Classifier: Programming Language :: Python :: 3
Classifier: Programming Language :: Python :: 3.13
Requires-Dist: fpdf2 (>=2.8.3,<3.0.0)
Requires-Dist: psutil (>=7.0.0,<8.0.0)
Requires-Dist: pyfiglet (>=1.0.2,<2.0.0)
Requires-Dist: rich (>=14.0.0,<15.0.0)
Requires-Dist: wmi (>=1.5.1,<2.0.0)
